dkc_api/__init__.py
dkc_api/v1/__init__.py
dkc_api/v1/const.py
dkc_api/v1/dkc_api.py
dkc_api/v1/storage.py
dkc_api/v1/models/__init__.py
dkc_api/v1/models/auth.py
dkc_api/v1/models/error.py
dkc_api-0.1.0.dist-info/LICENCE
dkc_api-0.1.0.dist-info/METADATA
dkc_api-0.1.0.dist-info/WHEEL
dkc_api-0.1.0.dist-info/top_level.txt
dkc_api-0.1.0.dist-info/RECORD
