Metadata-Version: 2.1
Name: dkc-api
Version: 0.1.0
Summary: Connector for connecting via api to DKC. Allows you to easily retrieve product and news data.
Home-page: https://github.com/Blackgard/dkc-api
Author: Alexandr Drachenin
Author-email: alexdrachenin98@gmail.com
License: MIT
Download-URL: https://github.com/Blackgard/dkc-api/tarball/v0.1.0
Keywords: python,dkc,api,connector,loader
Platform: UNKNOWN
Requires-Python: >=3.9
License-File: LICENCE
Requires-Dist: loguru (==0.5.3)
Requires-Dist: requests (==2.26.0)
Requires-Dist: pydantic (==1.8.2)
Requires-Dist: pytz (==2021.1)
Requires-Dist: python-dotenv (==0.19.0)
